Workbook
Name Slicer_Month: #N/A

Sheet Sheet1
A1: Field | B1: Value
A2: Model Name | B2: Reliance Health - Unit Economics Model
A3: Version | B3: v1.0
A4: Prepared For | B4: Hiring Manager/ Case Study
A5: Prepared By | B5: Dauda Abdullahi
A6: Date | B6: 46010
A7: Notes | B7: All inputs are in blue, formulas in black

Sheet Sheet2
A1: Time Settings
A2: Item | B2: Value
A3: Model Start Date | B3: 45658
A4: Model Periods (Months) | B4: 12
A9: Revenue Assumptions
A10: Item | B10: Value
A11: Price per Unit | B11: 20
A12: Starting Units Sold (Month 1) | B12: 1000
A13: Monthly Growth Rate | B13: 0.08
A18: Cost Assumptions
A19: Item | B19: Value
A20: Cost per Unit | B20: 120
A21: Fixed Operating Costs | B21: 2000
A22: Staff Salaries | B22: 25000
A23: Marketing Spend | B23: 10000
A27: Tax & Finance
A28: Item | B28: Value
A29: Tax Rate | B29: 0.3
A30: Starting Cash | B30: 50000

Sheet Sheet3
A1: Driver | B1: Cell | C1: Value
A2: Customer growth rate | B2: C2 | C2: 0.08
A3: Price per unit | B3: C3 | C3: 5000
A4: Units per customer | B4: C4 | C4: 2
A5: Conversion rate | B5: C5 | C5: 0.12
A6: Churn rate | B6: C6 | C6: 0.03
A10: Month | B10: Starting Customers | C10: Growth Rate | D10: New Customers | E10: Churn | F10: Ending Customers
A11: Jan | B11: 1000 | C11: =C2 -> 0.08 | D11: =B11*C2 -> 80 | E11: =B11*C6 -> 30 | F11: =B11+D11-E11 -> 1050
A12: Feb | B12: =F11 -> 1050 | C12: =C2 -> 0.08 | D12: =B12*C2 -> 84 | E12: =B12*C6 -> 31.5 | F12: =B12+D12-E12 -> 1102.5
A13: Mar | B13: =F12 -> 1102.5 | C13: =C2 -> 0.08 | D13: =B13*C2 -> 88.2 | E13: =B13*C6 -> 33.075 | F13: =B13+D13-E13 -> 1157.625
A14: Apr | B14: =F13 -> 1157.625 | C14: =C2 -> 0.08 | D14: =B14*C2 -> 92.61 | E14: =B14*C6 -> 34.72875 | F14: =B14+D14-E14 -> 1215.5062
A15: May | B15: =F14 -> 1215.5062 | C15: =C2 -> 0.08 | D15: =B15*C2 -> 97.2405 | E15: =B15*C6 -> 36.465187 | F15: =B15+D15-E15 -> 1276.2816
A16: Jun | B16: =F15 -> 1276.2816 | C16: =C2 -> 0.08 | D16: =B16*C2 -> 102.10252 | E16: =B16*C6 -> 38.288447 | F16: =B16+D16-E16 -> 1340.0956
A17: Jul | B17: =F16 -> 1340.0956 | C17: =C2 -> 0.08 | D17: =B17*C2 -> 107.20765 | E17: =B17*C6 -> 40.202869 | F17: =B17+D17-E17 -> 1407.1004
A18: Aug | B18: =F17 -> 1407.1004 | C18: =C2 -> 0.08 | D18: =B18*C2 -> 112.56803 | E18: =B18*C6 -> 42.213013 | F18: =B18+D18-E18 -> 1477.4554
A19: Sep | B19: =F18 -> 1477.4554 | C19: =C2 -> 0.08 | D19: =B19*C2 -> 118.19644 | E19: =B19*C6 -> 44.323663 | F19: =B19+D19-E19 -> 1551.3282
A20: Oct | B20: =F19 -> 1551.3282 | C20: =C2 -> 0.08 | D20: =B20*C2 -> 124.10626 | E20: =B20*C6 -> 46.539846 | F20: =B20+D20-E20 -> 1628.8946
A21: Nov | B21: =F20 -> 1628.8946 | C21: =C2 -> 0.08 | D21: =B21*C2 -> 130.31157 | E21: =B21*C6 -> 48.866839 | F21: =B21+D21-E21 -> 1710.3394
A22: Dec | B22: =F21 -> 1710.3394 | C22: =C2 -> 0.08 | D22: =B22*C2 -> 136.82715 | E22: =B22*C6 -> 51.310181 | F22: =B22+D22-E22 -> 1795.8563

Sheet Sheet4
A1: Driver | B1: Cell | C1: Value
A2: Price per Unit | B2: C2 | C2: 20
A3: Units per Customer | B3: C3 | C3: 2
A4: Discount Rate | B4: C4 | C4: 0.1
A5: ARPU | B5: C5 | C5: =C2*C3*(1-C4) -> 36
A6: Cost per Unit (COGS) | B6: C6 | C6: 120
A7: Fixed operating cost per month | B7: C7 | C7: 2000
A8: Marketing cost as % of revenue | B8: C8 | C8: 0.1
A13: Month | B13: Ending Customers | C13: ARPU | D13: Monthly Revenue | E13: Total Cost | F13: Profit | G13: Profit Margin | I13: Row Labels
A14: Jan | B14: =Sheet3!F11 -> 1050 | C14: =C5 -> 36 | D14: =B14*C5 -> 37800 | E14: =C7+(C8*D14) -> 5780 | F14: =D14-E14 -> 32020 | G14: =F14/D14 -> 0.84708995 | I14: Jan
A15: Feb | B15: =Sheet3!F12 -> 1102.5 | C15: =C5 -> 36 | D15: =B15*C5 -> 39690 | E15: =C7+(C8*D15) -> 5969 | F15: =D15-E15 -> 33721 | G15: =F15/D15 -> 0.84960947 | I15: Feb
A16: Mar | B16: =Sheet3!F13 -> 1157.625 | C16: =C5 -> 36 | D16: =B16*C5 -> 41674.5 | E16: =C7+(C8*D16) -> 6167.45 | F16: =D16-E16 -> 35507.05 | G16: =F16/D16 -> 0.85200902 | I16: Mar
A17: Apr | B17: =Sheet3!F14 -> 1215.5062 | C17: =C5 -> 36 | D17: =B17*C5 -> 43758.225 | E17: =$C$7+($C$8*D17) -> 6375.8225 | F17: =$D$17-$E$17 -> 37382.402 | G17: =F17/D17 -> 0.85429431 | I17: Apr
A18: May | B18: =Sheet3!F15 -> 1276.2816 | C18: =C5 -> 36 | D18: =B18*C5 -> 45946.136 | E18: =$C$7+($C$8*D18) -> 6594.6136 | F18: =D18-E18 -> 39351.523 | G18: =F18/D18 -> 0.85647077 | I18: May
A19: Jun | B19: =Sheet3!F16 -> 1340.0956 | C19: =C5 -> 36 | D19: =B19*C5 -> 48243.443 | E19: =$C$7+($C$8*D19) -> 6824.3443 | F19: =D19-E19 -> 41419.099 | G19: =F19/D19 -> 0.85854359 | I19: Jun
A20: Jul | B20: =Sheet3!F17 -> 1407.1004 | C20: =C5 -> 36 | D20: =B20*C5 -> 50655.615 | E20: =$C$7+($C$8*D20) -> 7065.5615 | F20: =D20-E20 -> 43590.054 | G20: =F20/D20 -> 0.8605177 | I20: Jul
A21: Aug | B21: =Sheet3!F18 -> 1477.4554 | C21: =C5 -> 36 | D21: =B21*C5 -> 53188.396 | E21: =$C$7+($C$8*D21) -> 7318.8396 | F21: =D21-E21 -> 45869.556 | G21: =F21/D21 -> 0.86239781 | I21: Aug
A22: Sep | B22: =Sheet3!F19 -> 1551.3282 | C22: =C5 -> 36 | D22: =B22*C5 -> 55847.816 | E22: =$C$7+($C$8*D22) -> 7584.7816 | F22: =D22-E22 -> 48263.034 | G22: =F22/D22 -> 0.86418839 | I22: Sep
A23: Oct | B23: =Sheet3!F20 -> 1628.8946 | C23: =C5 -> 36 | D23: =B23*C5 -> 58640.207 | E23: =$C$7+($C$8*D23) -> 7864.0207 | F23: =D23-E23 -> 50776.186 | G23: =F23/D23 -> 0.86589371 | I23: Oct
A24: Nov | B24: =Sheet3!F21 -> 1710.3394 | C24: =C5 -> 36 | D24: =B24*C5 -> 61572.217 | E24: =$C$7+($C$8*D24) -> 8157.2217 | F24: =D24-E24 -> 53414.995 | G24: =F24/D24 -> 0.86751782 | I24: Nov
A25: Dec | B25: =Sheet3!F22 -> 1795.8563 | C25: =C5 -> 36 | D25: =B25*C5 -> 64650.828 | E25: =$C$7+($C$8*D25) -> 8465.0828 | F25: =D25-E25 -> 56185.745 | G25: =F25/D25 -> 0.86906459 | I25: Dec
I26: Grand Total

Sheet Sheet5
A1: KPI | B1: Formula | C1: Value
A2: Total Revenue | C2: =SUM(Sheet4!F14:F25) -> 517500.64
A3: Total Cost | C3: =SUM(Sheet4!E14:E25) -> 84166.738
A4: Profit | C4: =C2-C3 -> 433333.91
A5: Profit Margin | C5: =C4/C2 -> 0.83735916

Sheet Sheet6
A1: Financial Performance Dashboard
A4: Total Revenue | B4: Total Cost | C4: Total Profit | D4: Profit Margin
A5: =Sheet5!C2 -> 517500.64 | B5: =Sheet5!C3 -> 84166.738 | C5: =Sheet5!C4 -> 433333.91 | D5: =Sheet5!C5 -> 0.83735916
A9: Month | B9: Revenue | C9: Cost | D9: Profit Margin
A10: Jan | B10: =Sheet4!D14 -> 37800 | C10: =Sheet4!E14 -> 5780 | D10: =Sheet4!G14 -> 0.84708995
A11: Feb | B11: =Sheet4!D15 -> 39690 | C11: =Sheet4!E15 -> 5969 | D11: =Sheet4!G15 -> 0.84960947
A12: Mar | B12: =Sheet4!D16 -> 41674.5 | C12: =Sheet4!E16 -> 6167.45 | D12: =Sheet4!G16 -> 0.85200902
A13: Apr | B13: =Sheet4!D17 -> 43758.225 | C13: =Sheet4!E17 -> 6375.8225 | D13: =Sheet4!G17 -> 0.85429431
A14: May | B14: =Sheet4!D18 -> 45946.136 | C14: =Sheet4!E18 -> 6594.6136 | D14: =Sheet4!G18 -> 0.85647077
A15: Jun | B15: =Sheet4!D19 -> 48243.443 | C15: =Sheet4!E19 -> 6824.3443 | D15: =Sheet4!G19 -> 0.85854359
A16: Jul | B16: =Sheet4!D20 -> 50655.615 | C16: =Sheet4!E20 -> 7065.5615 | D16: =Sheet4!G20 -> 0.8605177
A17: Aug | B17: =Sheet4!D21 -> 53188.396 | C17: =Sheet4!E21 -> 7318.8396 | D17: =Sheet4!G21 -> 0.86239781
A18: Sep | B18: =Sheet4!D22 -> 55847.816 | C18: =Sheet4!E22 -> 7584.7816 | D18: =Sheet4!G22 -> 0.86418839
A19: Oct | B19: =Sheet4!D23 -> 58640.207 | C19: =Sheet4!E23 -> 7864.0207 | D19: =Sheet4!G23 -> 0.86589371
A20: Nov | B20: =Sheet4!D24 -> 61572.217 | C20: =Sheet4!E24 -> 8157.2217 | D20: =Sheet4!G24 -> 0.86751782
A21: Dec | B21: =Sheet4!D25 -> 64650.828 | C21: =Sheet4!E25 -> 8465.0828 | D21: =Sheet4!G25 -> 0.86906459

Sheet Sheet7 - Sentivity Analysis
A1: Sensitivity Analysis - ARPU impact on Profit
A3: ARPU Change | B3: ARPU Value | C3: Profit
A4: -0.2 | B4: =Sheet4!$C$5*(1+A4) -> 28.8 | C4: =Sheet6!C5 -> 433333.91
A5: -0.1 | B5: =Sheet4!C5*(1+A5) -> 32.4 | C5: 385200.52
A6: 0 | B6: =Sheet4!C5*(1+A6) -> 36 | C6: 385200.52
A7: 0.1 | B7: =Sheet4!C5*(1+A7) -> 39.6 | C7: 428520.57
A8: 0.2 | B8: =Sheet4!C5*(1+A8) -> 43.2 | C8: 523824.68
A9: 0.3 | B9: =Sheet4!C5*(1+A9) -> 46.8 | C9: 695372.08
A13: Price Change | B13: Profit
A14: -0.2 | B14: -52813.339
A15: -0.1 | B15: -50406.67
A16: 0 | B16: -48000
A17: 0.1 | B17: -45593.33
A18: 0.2 | B18: -43186.661
A19: 0.3 | B19: -40779.991

Sheet Sheet8
A1: Driver | B1: Low Case (-20%) | C1: High Case (+20%) | D1: Low Impact | E1: High Impact | F1: Impact
A2: Price per unit | B2: 337067.12 | C2: 529600.69 | D2: =337067.1248-(-48000) -> 385067.12 | E2: =529600.6872-(-48000) -> 577600.69 | F2: =577600.6872-385067.1248 -> 192533.56
A3: Units per customer | B3: 337067.12 | C3: 529600.69 | D3: 385067.12 | E3: 577600.69 | F3: =577600.6872-385067.1248 -> 192533.56
A4: Discount rate | B4: -3791708.2 | C4: -5930970 | D4: =(-3791708.16)-(-48000) -> -3743708.2 | E4: =(-5930969.96)-(-48000) -> -5882970 | F4: =(-5882969.96)-(-3743708.16) -> -2139261.8

Sheet Sheet9
A1: Item | B1: Value
A2: ARPU | B2: =Sheet4!C5 -> 36
A3: Fixed Costs | B3: =Sheet4!C7 -> 2000
A4: Break-Even Customers | B4: =Sheet9!B3/Sheet9!B2 -> 55.555556
A5: Break-Even Price | B5: =(B3/B4)+D14 -> 4036
D14: =Sheet4!C7*Sheet4!C3 -> 4000

Sheet Sheet10
A1: Customer | B1: Revenue | C1: Total Cost | H1: Customers | I1: Break-Even Line
A2: 1000 | B2: =A2*Sheet4!C5 -> 36000 | C2: =Sheet4!C7+(A2*Sheet4!C6) -> 122000 | H2: 3214 | I2: 0
A3: 2000 | B3: =A3*Sheet4!C5 -> 72000 | C3: =Sheet4!C7+(A3*Sheet4!C6) -> 242000 | H3: 3214 | I3: 180000
A4: 3000 | B4: =A4*Sheet4!C5 -> 108000 | C4: =Sheet4!C7+(A4*Sheet4!C6) -> 362000
A5: 4000 | B5: =A5*Sheet4!C5 -> 144000 | C5: =Sheet4!C7+(A5*Sheet4!C6) -> 482000
A6: 5000 | B6: =A6*Sheet4!C5 -> 180000 | C6: =Sheet4!C7+(A6*Sheet4!C6) -> 602000

Sheet Monthly Ramp to Break-Even
B1: Label | C1: Value
B2: Starting Customers | C2: 1000
B3: Monthly Customer Growth | C3: 0.08
B4: Fixed Costs (One-off) | C4: 150000
A5: Month | B5: Value | C5: Revenue | D5: Cost | E5: Profit | F5: Cumulative Profit | G5: Break-Even Flag
A6: Month 1 | B6: =$C$2 -> 1000 | C6: =B6*Sheet4!$C$5 -> 36000 | D6: =Sheet4!$C$7 -> 2000 | E6: =C6-D6-$C$4 -> -116000 | F6: =E6 -> -116000 | G6: =IF(F6>=0, "Break-Even", " ")
A7: Month 2 | B7: =B6*(1+$C$3) -> 1080 | C7: =B7*Sheet4!$C$5 -> 38880 | D7: =Sheet4!$C$7 -> 2000 | E7: =C7-D7 -> 36880 | F7: =F6+E7 -> -79120 | G7: =IF(F7>=0, "Break-Even", " ")
A8: Month 3 | B8: =B7*(1+$C$3) -> 1166.4 | C8: =B8*Sheet4!$C$5 -> 41990.4 | D8: =Sheet4!$C$7 -> 2000 | E8: =C8-D8 -> 39990.4 | F8: =F7+E8 -> -39129.6 | G8: =IF(F8>=0, "Break-Even", " ")
A9: Month 4 | B9: =B8*(1+$C$3) -> 1259.712 | C9: =B9*Sheet4!$C$5 -> 45349.632 | D9: =Sheet4!$C$7 -> 2000 | E9: =C9-D9 -> 43349.632 | F9: =F8+E9 -> 4220.032 | G9: =IF(F9>=0, "Break-Even", " ") -> Break-Even
A10: Month 5 | B10: =B9*(1+$C$3) -> 1360.489 | C10: =B10*Sheet4!$C$5 -> 48977.603 | D10: =Sheet4!$C$7 -> 2000 | E10: =C10-D10 -> 46977.603 | F10: =F9+E10 -> 51197.635
A11: Month 6 | B11: =B10*(1+$C$3) -> 1469.3281 | C11: =B11*Sheet4!$C$5 -> 52895.811 | D11: =Sheet4!$C$7 -> 2000 | E11: =C11-D11 -> 50895.811 | F11: =F10+E11 -> 102093.45
A12: Month 7 | B12: =B11*(1+$C$3) -> 1586.8743 | C12: =B12*Sheet4!$C$5 -> 57127.476 | D12: =Sheet4!$C$7 -> 2000 | E12: =C12-D12 -> 55127.476 | F12: =F11+E12 -> 157220.92
A13: Month 8 | B13: =B12*(1+$C$3) -> 1713.8243 | C13: =B13*Sheet4!$C$5 -> 61697.674 | D13: =Sheet4!$C$7 -> 2000 | E13: =C13-D13 -> 59697.674 | F13: =F12+E13 -> 216918.59
A14: Month 9 | B14: =B13*(1+$C$3) -> 1850.9302 | C14: =B14*Sheet4!$C$5 -> 66633.488 | D14: =Sheet4!$C$7 -> 2000 | E14: =C14-D14 -> 64633.488 | F14: =F13+E14 -> 281552.08
A15: Month 10 | B15: =B14*(1+$C$3) -> 1999.0046 | C15: =B15*Sheet4!$C$5 -> 71964.167 | D15: =Sheet4!$C$7 -> 2000 | E15: =C15-D15 -> 69964.167 | F15: =F14+E15 -> 351516.25
A16: Month 11 | B16: =B15*(1+$C$3) -> 2158.925 | C16: =B16*Sheet4!$C$5 -> 77721.3 | D16: =Sheet4!$C$7 -> 2000 | E16: =C16-D16 -> 75721.3 | F16: =F15+E16 -> 427237.55
A17: Month 12 | B17: =B16*(1+$C$3) -> 2331.639 | C17: =B17*Sheet4!$C$5 -> 83939.004 | D17: =Sheet4!$C$7 -> 2000 | E17: =C17-D17 -> 81939.004 | F17: =F16+E17 -> 509176.55

Sheet Sheet11
A1: Financial Model Executive Summary | F1: Break-even achieved in Month 4
A15: Profit Sentivity (Top Drivers)
F17: Key Insights & Recommendations
F18: 1. Profitability is most sensitive toPrice per Unit and ARPU
F19: 2. Break-even occurs after achieving sustained customer growth
F20: 3. Discounting materially delays profitability
F22: Recommendation: Focus on pricing discipline and ARPU optimization to accelerate break-even.
